py_wlcommands/__init__.py
py_wlcommands/__main__.py
py_wlcommands/cli.py
py_wlcommands/cli_click.py
py_wlcommands/commands/__init__.py
py_wlcommands/commands/base.py
py_wlcommands/commands/buildcommands/__init__.py
py_wlcommands/commands/buildcommands/build.py
py_wlcommands/commands/buildcommands/build_utils.py
py_wlcommands/commands/buildcommands/builders/__init__.py
py_wlcommands/commands/buildcommands/builders/cleanup.py
py_wlcommands/commands/buildcommands/builders/coordinator.py
py_wlcommands/commands/buildcommands/builders/environment.py
py_wlcommands/commands/buildcommands/builders/rust_builder.py
py_wlcommands/commands/buildcommands/builders/stubs.py
py_wlcommands/commands/buildcommands/dist.py
py_wlcommands/commands/buildcommands/test.py
py_wlcommands/commands/clean/__init__.py
py_wlcommands/commands/clean/clean.py
py_wlcommands/commands/clean/clean_utils.py
py_wlcommands/commands/clean/cleaners/__init__.py
py_wlcommands/commands/clean/cleaners/build_cleaner.py
py_wlcommands/commands/clean/cleaners/coordinator.py
py_wlcommands/commands/clean/cleaners/lfs_cleaner.py
py_wlcommands/commands/clean/utils/__init__.py
py_wlcommands/commands/clean/utils/core_cleaners.py
py_wlcommands/commands/clean/utils/python_cleaners.py
py_wlcommands/commands/clean/utils/rust_cleaners.py
py_wlcommands/commands/clean/utils/venv_cleaners.py
py_wlcommands/commands/command_adapter.py
py_wlcommands/commands/command_loader.py
py_wlcommands/commands/command_registry.py
py_wlcommands/commands/config/__init__.py
py_wlcommands/commands/config/config.py
py_wlcommands/commands/decorators.py
py_wlcommands/commands/dependency_resolver.py
py_wlcommands/commands/error_codes.py
py_wlcommands/commands/format/__init__.py
py_wlcommands/commands/format/format_command.py
py_wlcommands/commands/format/format_coordinator.py
py_wlcommands/commands/format/format_path_handler.py
py_wlcommands/commands/format/format_reporter.py
py_wlcommands/commands/format/python_formatter.py
py_wlcommands-0.2.48.dist-info/METADATA
py_wlcommands-0.2.48.dist-info/WHEEL
py_wlcommands-0.2.48.dist-info/entry_points.txt
py_wlcommands-0.2.48.dist-info/licenses/LICENSE
py_wlcommands-0.2.48.dist-info/RECORD
