Metadata-Version: 2.4
Name: py_wlcommands
Version: 0.2.48
Requires-Dist: toml>=0.10.2
Requires-Dist: tomli>=2.3.0
Requires-Dist: pathspec>=0.12.1
Requires-Dist: aiohttp>=3.13.2
Requires-Dist: click>=8.1.0
Requires-Dist: pytest-asyncio>=1.3.0
Requires-Dist: tqdm>=4.66.0
Requires-Dist: types-tqdm>=4.67.0.20250809
Requires-Dist: pytest>=9.0.1 ; extra == 'dev'
Requires-Dist: mypy>=1.18.2 ; extra == 'dev'
Requires-Dist: pytest-cov>=7.0.0 ; extra == 'dev'
Requires-Dist: pytest-asyncio>=1.3.0 ; extra == 'dev'
Requires-Dist: ruff>=0.14.0 ; extra == 'dev'
Requires-Dist: types-toml>=0.10.8.20240310 ; extra == 'dev'
Requires-Dist: pre-commit>=4.5.0 ; extra == 'dev'
Requires-Dist: pytest-xdist>=3.8.0 ; extra == 'dev'
Requires-Dist: twine>=6.2.0 ; extra == 'dev'
Provides-Extra: dev
License-File: LICENSE
License-File: LICENSE
Summary: py_wlcommands - Python项目
Author-email: WL Admin <wl.admin@example.com>
Requires-Python: >=3.10
Project-URL: Homepage, https://github.com/wl-commands/py_wlcommands
Project-URL: Issues, https://github.com/wl-commands/py_wlcommands/issues
